<?xml version="1.0" encoding="UTF-8"?><record_update>
    <sys_choice action="DELETE" field="u_what_needed" table="x_58872_needit_needit" version="3">
        <sys_choice_set action="DELETE">
            <element>u_what_needed</element>
            <name>x_58872_needit_needit</name>
            <sys_class_name/>
            <sys_created_by/>
            <sys_created_on/>
            <sys_id/>
            <sys_mod_count/>
            <sys_name/>
            <sys_package/>
            <sys_policy/>
            <sys_scope/>
            <sys_update_name/>
            <sys_updated_by/>
            <sys_updated_on>2020-02-12 08:05:43</sys_updated_on>
        </sys_choice_set>
    </sys_choice>
    <sys_update_version action="INSERT_OR_UPDATE">
        <action>DELETE</action>
        <application/>
        <file_path/>
        <instance_id>1a50f30c6f175240f51e7b2f5d3ee430</instance_id>
        <instance_name>dev24178</instance_name>
        <name>sys_choice_x_58872_needit_needit_u_what_needed</name>
        <payload><![CDATA[<?xml version="1.0" encoding="UTF-8"?><record_update><sys_choice action="DELETE" field="u_what_needed" table="x_58872_needit_needit" version="3"><sys_choice_set action="DELETE"><element>u_what_needed</element><name>x_58872_needit_needit</name><sys_class_name/><sys_created_by/><sys_created_on/><sys_id/><sys_mod_count/><sys_name/><sys_package/><sys_policy/><sys_scope/><sys_update_name/><sys_updated_by/><sys_updated_on>2020-02-12 08:05:43</sys_updated_on></sys_choice_set></sys_choice></record_update>]]></payload>
        <payload_hash>-429457270</payload_hash>
        <record_name>Task.u_what_needed</record_name>
        <reverted_from/>
        <source>909fc9dbdb7200102326560868961986</source>
        <source_table>sys_update_set</source_table>
        <state>previous</state>
        <sys_created_by>admin</sys_created_by>
        <sys_created_on>2020-02-12 08:05:43</sys_created_on>
        <sys_id>f4c369a3db32001023265608689619fa</sys_id>
        <sys_mod_count>0</sys_mod_count>
        <sys_recorded_at>170386eb1b50000001</sys_recorded_at>
        <sys_updated_by>admin</sys_updated_by>
        <sys_updated_on>2020-02-12 08:05:43</sys_updated_on>
        <type>Choice list</type>
        <update_guid>70c369a3c23200105d9bfcb8ee939cfa</update_guid>
        <update_guid_history>70c369a3c23200105d9bfcb8ee939cfa:-429457270,7cc369a3603200106a52c7c1bc9f54f6:-356377995,3cc369a35b32001058aa3c9da03d2af3:1008369778,e8c369a39f320010079385b9f0ee74f0:1793394304,a8c369a34b3200103e977c18173061ed:60889329,68c369a3dc32001062f0c4e9e7bd36ea:-334244309,28c369a3b7320010f3aaa3167c2a1ce7:-1795993788,e4c369a3cb3200104592ac2e70b89fe4:1989655492,b40fd11ff0b200104b6ac1b6ae6cd8eb:25275431</update_guid_history>
    </sys_update_version>
    <sys_metadata_delete action="INSERT_OR_UPDATE">
        <sys_audit_delete/>
        <sys_class_name>sys_metadata_delete</sys_class_name>
        <sys_created_by>admin</sys_created_by>
        <sys_created_on>2020-02-12 08:05:59</sys_created_on>
        <sys_db_object display_value="" name="sys_choice_set">sys_choice_set</sys_db_object>
        <sys_id>40d32da3db320010232656086896194e</sys_id>
        <sys_metadata>40d32da3db320010232656086896194e</sys_metadata>
        <sys_mod_count>0</sys_mod_count>
        <sys_name>u_what_needed</sys_name>
        <sys_package display_value="NeedIt" source="x_58872_needit">6ead8e780f603200cd674f8ce1050ed1</sys_package>
        <sys_parent/>
        <sys_policy/>
        <sys_scope display_value="NeedIt">6ead8e780f603200cd674f8ce1050ed1</sys_scope>
        <sys_scope_delete display_value="">94872a8897db403e8ee69a431de2fca4</sys_scope_delete>
        <sys_update_name>sys_choice_x_58872_needit_needit_u_what_needed</sys_update_name>
        <sys_update_version display_value="sys_choice_x_58872_needit_needit_u_what_needed">f4c369a3db32001023265608689619fa</sys_update_version>
        <sys_updated_by>admin</sys_updated_by>
        <sys_updated_on>2020-02-12 08:05:59</sys_updated_on>
    </sys_metadata_delete>
</record_update>
